HISTORY.txt
LICENSE
MANIFEST.in
README.md
requirements.txt
setup.cfg
setup.py
rcsb/__init__.py
rcsb.app.template.egg-info/PKG-INFO
rcsb.app.template.egg-info/SOURCES.txt
rcsb.app.template.egg-info/dependency_links.txt
rcsb.app.template.egg-info/not-zip-safe
rcsb.app.template.egg-info/requires.txt
rcsb.app.template.egg-info/top_level.txt
rcsb/app/__init__.py
rcsb/app/template/ConfigProvider.py
rcsb/app/template/LogFilterUtils.py
rcsb/app/template/__init__.py
rcsb/app/template/main.py
rcsb/app/template/serverStatus.py