Metadata-Version: 2.1
Name: rcsb.app.template
Version: 0.15
Summary: RCSB Application Template
Home-page: https://github.com/rcsb/py-rcsb_app_template
Author: John Westbrook
Author-email: john.westbrook@rcsb.org
License: Apache 2.0
Classifier: Development Status :: 3 - Alpha
Classifier: Intended Audience :: Developers
Classifier: Natural Language :: English
Classifier: License :: OSI Approved :: Apache Software License
Classifier: Programming Language :: Python
Classifier: Programming Language :: Python :: 3
Classifier: Programming Language :: Python :: 3.9
Provides-Extra: dev
Provides-Extra: test
License-File: LICENSE
